setup.py
WixOS/main.py
WixOS.egg-info/PKG-INFO
WixOS.egg-info/SOURCES.txt
WixOS.egg-info/dependency_links.txt
WixOS.egg-info/entry_points.txt
WixOS.egg-info/requires.txt
WixOS.egg-info/top_level.txt