Metadata-Version: 2.1
Name: WixOS
Version: 1.1.1
Summary: WixOS Package
Author: Aras Tokdemir
Author-email: aras.tokdemir@outlook.com
